pycvi/__init__.py
pycvi/external/__init__.py
pycvi/external/purity.py
pycvi/internal/__init__.py
pycvi/internal/davies_bouldin.py
pycvi/utils/__init__.py
pycvi/utils/dataset.py
pycvi/utils/distances.py
pycvi/utils/features.py
pycvi/utils/labels.py
pycvi/utils/parse.py
tests/__init__.py
tests/test_dataset.py
tests/test_davies_bouldin.py
tests/test_labels.py
tests/test_parse.py
tests/test_purity.py
pycvi-0.0.13.dist-info/LICENSE
pycvi-0.0.13.dist-info/METADATA
pycvi-0.0.13.dist-info/WHEEL
pycvi-0.0.13.dist-info/top_level.txt
pycvi-0.0.13.dist-info/RECORD
