Metadata-Version: 2.1
Name: pycvi
Version: 0.0.13
Summary: Easily compute clustering cliterions
Home-page: UNKNOWN
Author: Yohan Foucade
Author-email: foucade@lipn.fr
License: MIT
Platform: UNKNOWN
Requires-Dist: numpy
Requires-Dist: pandas
Requires-Dist: scikit-learn
